[
    {
        "name": "id_entrevista",
        "dbType": "integer,true",
        "htmlType": null,
        "validations": null,
        "searchable": false,
        "fillable": false,
        "primary": true,
        "inForm": false,
        "inIndex": false
    },
    {
        "name": "id_e_ind_fvt",
        "dbType": "integer,false",
        "htmlType": null,
        "validations": "required",
        "searchable": true,
        "fillable": true,
        "primary": false,
        "inForm": true,
        "inIndex": true
    },
    {
        "name": "id_idioma",
        "dbType": "integer,false",
        "htmlType": null,
        "validations": "required",
        "searchable": true,
        "fillable": true,
        "primary": false,
        "inForm": true,
        "inIndex": true
    },
    {
        "name": "id_nativo",
        "dbType": "integer,false",
        "htmlType": null,
        "validations": null,
        "searchable": true,
        "fillable": true,
        "primary": false,
        "inForm": true,
        "inIndex": true
    },
    {
        "name": "nombre_interprete",
        "dbType": "string",
        "htmlType": "text",
        "validations": null,
        "searchable": true,
        "fillable": true,
        "primary": false,
        "inForm": true,
        "inIndex": true
    },
    {
        "name": "documentacion_aporta",
        "dbType": "integer,false",
        "htmlType": null,
        "validations": "required",
        "searchable": true,
        "fillable": true,
        "primary": false,
        "inForm": true,
        "inIndex": true
    },
    {
        "name": "documentacion_especificar",
        "dbType": "text",
        "htmlType": "textarea",
        "validations": null,
        "searchable": true,
        "fillable": true,
        "primary": false,
        "inForm": true,
        "inIndex": true
    },
    {
        "name": "identifica_testigos",
        "dbType": "integer,false",
        "htmlType": null,
        "validations": "required",
        "searchable": true,
        "fillable": true,
        "primary": false,
        "inForm": true,
        "inIndex": true
    },
    {
        "name": "ampliar_relato",
        "dbType": "integer,false",
        "htmlType": null,
        "validations": "required",
        "searchable": true,
        "fillable": true,
        "primary": false,
        "inForm": true,
        "inIndex": true
    },
    {
        "name": "ampliar_relato_temas",
        "dbType": "text",
        "htmlType": "textarea",
        "validations": null,
        "searchable": true,
        "fillable": true,
        "primary": false,
        "inForm": true,
        "inIndex": true
    },
    {
        "name": "priorizar_entrevista",
        "dbType": "integer,false",
        "htmlType": null,
        "validations": "required",
        "searchable": true,
        "fillable": true,
        "primary": false,
        "inForm": true,
        "inIndex": true
    },
    {
        "name": "priorizar_entrevista_asuntos",
        "dbType": "text",
        "htmlType": "textarea",
        "validations": null,
        "searchable": true,
        "fillable": true,
        "primary": false,
        "inForm": true,
        "inIndex": true
    },
    {
        "name": "contiene_patrones",
        "dbType": "integer,false",
        "htmlType": null,
        "validations": "required",
        "searchable": true,
        "fillable": true,
        "primary": false,
        "inForm": true,
        "inIndex": true
    },
    {
        "name": "contiene_patrones_cuales",
        "dbType": "text",
        "htmlType": "textarea",
        "validations": null,
        "searchable": true,
        "fillable": true,
        "primary": false,
        "inForm": true,
        "inIndex": true
    },
    {
        "name": "indicaciones_transcripcion",
        "dbType": "text",
        "htmlType": "textarea",
        "validations": null,
        "searchable": true,
        "fillable": true,
        "primary": false,
        "inForm": true,
        "inIndex": true
    },
    {
        "name": "observaciones",
        "dbType": "text",
        "htmlType": "textarea",
        "validations": null,
        "searchable": true,
        "fillable": true,
        "primary": false,
        "inForm": true,
        "inIndex": true
    },
    {
        "name": "created_at",
        "dbType": "datetime",
        "htmlType": "date",
        "validations": null,
        "searchable": true,
        "fillable": true,
        "primary": false,
        "inForm": true,
        "inIndex": true
    },
    {
        "name": "updated_at",
        "dbType": "datetime",
        "htmlType": "date",
        "validations": null,
        "searchable": true,
        "fillable": true,
        "primary": false,
        "inForm": true,
        "inIndex": true
    },
    {
        "type": "relation",
        "relation": "mt1,Esclarecimiento.eIndFvt,id_e_ind_fvt"
    },
    {
        "type": "relation",
        "relation": "mt1,Catalogos.catItem,id_idioma"
    },
    {
        "type": "relation",
        "relation": "mt1,Catalogos.catItem,id_nativo"
    },
    {
        "type": "relation",
        "relation": "mtm,Catalogos.catItem,fichas.entrevista_condiciones"
    },
    {
        "type": "relation",
        "relation": "1tm,Fichas.entrevistaTestigo,id_entrevista"
    }
]